[
  {
    "id": 6,
    "image": "portfolio6.jpg",
    "title": "Persöhnliche Portfolio Website",
    "github": "https://github.com",
    "demo": "https://google.com"
  },
  {
    "id": 5,
    "image": "portfolio1.jpg",
    "title": "Neu- und Weiterentwicklung der internen IT-Landschaft zur Verarbeitung fachlicher Anwendungsfälle",
    "github": "https://github.com",
    "demo": "https://google.com"
  },
  {
    "id": 4,
    "image": "portfolio2.jpg",
    "title": "Entwicklung eines PDSG-konformen Verifizierungs- und Authenti-fizierungstools inkl. Anbindung eines VideoIdent-Verfahrens",
    "github": "https://github.com",
    "demo": "https://google.com"
  },
  {
    "id": 3,
    "image": "portfolio3.jpg",
    "title": "Weiterentwicklung einer Versicherungssoftware",
    "github": "https://github.com",
    "demo": "https://google.com"
  },
  {
    "id": 2,
    "image": "portfolio4.jpg",
    "title": "Entwicklung einer Personendatenbank auf Basis des Open Source CRM-Systems „SuiteCRM“",
    "github": "https://github.com",
    "demo": "https://google.com"
  },
  {
    "id": 1,
    "image": "portfolio5.png",
    "title": "Ablösung von diversen IBM Notes-Anwendungen durch neu entwickelte Webanwendungen",
    "github": "https://github.com",
    "demo": "https://google.com"
  }
]
